LICENSE
MANIFEST.in
README.md
setup.py
weakpoint/__init__.py
weakpoint/config.py
weakpoint/core.py
weakpoint/exceptions.py
weakpoint/fs.py
weakpoint/main.py
weakpoint/renderers.py
weakpoint/slides.py
weakpoint/utils.py
weakpoint.egg-info/PKG-INFO
weakpoint.egg-info/SOURCES.txt
weakpoint.egg-info/dependency_links.txt
weakpoint.egg-info/entry_points.txt
weakpoint.egg-info/not-zip-safe
weakpoint.egg-info/requires.txt
weakpoint.egg-info/top_level.txt
weakpoint/parsers/__init__.py
weakpoint/parsers/markdown.py
weakpoint/themes/dark/config.yaml
weakpoint/themes/dark/index.html
weakpoint/themes/dark/slides.md
weakpoint/themes/dark/_templates/footer.html
weakpoint/themes/dark/_templates/header.html
weakpoint/themes/dark/_templates/layout.html
weakpoint/themes/dark/_templates/_settings/analytics.html
weakpoint/themes/dark/_templates/_settings/font.html
weakpoint/themes/dark/_templates/_settings/latex.html
weakpoint/themes/dark/_templates/_slides/content.html
weakpoint/themes/dark/_templates/_slides/cover.html
weakpoint/themes/dark/_templates/_slides/navi.html
weakpoint/themes/dark/assets/css/style.css
weakpoint/themes/dark/assets/js/impress.js
weakpoint/themes/light/config.yaml
weakpoint/themes/light/slides.md
weakpoint/themes/light/_templates/footer.html
weakpoint/themes/light/_templates/header.html
weakpoint/themes/light/_templates/layout.html
weakpoint/themes/light/_templates/_settings/analytics.html
weakpoint/themes/light/_templates/_settings/font.html
weakpoint/themes/light/_templates/_settings/latex.html
weakpoint/themes/light/_templates/_slides/content.html
weakpoint/themes/light/_templates/_slides/cover.html
weakpoint/themes/light/_templates/_slides/navi.html
weakpoint/themes/light/assets/css/style.css
weakpoint/themes/light/assets/js/impress.js